Workbook
Name \aq: #REF!
Name \aq: #REF!
Name \aq: #REF!
Name \c: #REF!
Name \c: #REF!
Name \e: #REF!
Name \e: #REF!
Name \f: #REF!
Name \f: #REF!
Name \l: #REF!
Name \l: #REF!
Name \l: #REF!
Name \p: #REF!
Name \p: #REF!
Name \p: #REF!
Name \q: #REF!
Name \q: #REF!
Name \s: '[1]Originating Station'!#REF!
Name \s: '[2]Originating Station'!#REF!
Name \u: '[1]Originating Station'!#REF!
Name \u: '[2]Originating Station'!#REF!
Name \w: #REF!
Name \w: #REF!
Name \x: #REF!
Name \x: #REF!
Name \y: '[3]SCADA(MCC-SCC)-Koyali'!#REF!
Name \z: #N/A
Name ______________DEF1: #REF!
Name ______________DEF1: #REF!
Name ______________DEF2: #REF!
Name ______________DEF2: #REF!
Name ______________SE1: #REF!
Name ______________SE1: #REF!
Name ______________SET1: #REF!
Name ______________SET1: #REF!
Name ______________SET2: #REF!
Name ______________SET2: #REF!
Name ______________SET21: #REF!
Name ______________SET21: #REF!
Name ______________TB2: '[4]SPT vs PHI'!$B$2:$C$65
Name ______________TB2: #REF!
Name _____________DEF1: #REF!
Name _____________DEF1: #REF!
Name _____________DEF2: #REF!
Name _____________DEF2: #REF!
Name _____________SE1: #REF!
Name _____________SE1: #REF!
Name _____________SET1: #REF!
Name _____________SET1: #REF!
Name _____________SET2: #REF!
Name _____________SET2: #REF!
Name _____________SET21: #REF!
Name _____________SET21: #REF!
Name _____________TB2: '[4]SPT vs PHI'!$B$2:$C$65
Name _____________TB2: #REF!
Name ____________DEF1: #REF!
Name ____________DEF1: #REF!
Name ____________DEF2: #REF!
Name ____________DEF2: #REF!
Name ____________SE1: #REF!

Sheet Summary
G2: Client Name : | H2: NIPI
G3: Account Lead : | H3: Ravi S
G4: Date : | H4: 45771
G5: Validity : | H5: NA
G7: Client Name:- | H7: NIPI
C9: Sr. No. | D9: Item Wise Amounts (Exclusive of Taxes) | E9: Total Monthly Cost | F9: Duration | G9: Total Cost | H9: OTC
C10: Data Center Site
C11: 1 | D11: Hosting cost for - Primary Site (DC) | E11: ='DC Site'!F28 -> 76190 | F11: 12 | G11: =E11*F11 -> 914280 | H11: ='DC Site'!G28 -> 0
C12: 2 | D12: Cloud Hosting for Primary Site | E12: ='Primary site'!F22 -> 8292 | F12: 12 | G12: =E12*F12 -> 99504
C13: Total cost | G13: =SUM(G11:G12) -> 1013784 | H13: =SUM(H11:H11) -> 0
C15: Grand total cost with Total DC- Without Taxes | G15: =G13+H13 -> 1013784
B19: Terms & Conditions:
B20: Price:
B21: • All prices are in Indian Rupee without Taxes
B22: • Any change in the taxes, duties or levies due to change in government policies will be borne by the customer.
B23: • Billing shall start from the date of infrastructure hand-over in partial or full, irrespective of the Go-Live of the project, for e.g Dev environment is setup and released to client/partner for development activity, then the billing for the Dev enviornment will start immediately after Development environment is handed over to department / partner, similarly for any other environment, what ever is handed over, billing will start immediately after that.
B24: • The quote is valid for 30 days from the date of submission of offer.
B25: • Infrastructure setup will be done based on the finalized and approved BoM and architecture, in case any change need to be done, then it will be considerd as a change request and charges for the same will be additional.
B26: • Prices are composite for the total Bill of Material and may vary with change in the Bill of Material due to increase or decrease in quantity/service period at the time of ordering.
B27: • Software which are proposed in the BoM with default features, if any specifc features is required then the charges for the same would be extra.
B29: Payment Terms:
B30: • One Time Charges (OTC) to be paid in advance along with Purchase Order.
B31: • Recurring charges (RC) payable as per RFP terms. Invoice will be generated and shared.
... B61: • The above data center(s) are selected as per availability of the resources at the respective facilities as on date. ESDS reserves the right to change DC/DR location within India at any point of time subjected to availability of resources, the same shall be compliant to the requirement.

Sheet DC Site
B2: ESDS Cloud Hosting Services - Primary Site (DC Site) | J2: Compute
J3: ='Discount Sheet'!G5 -> 120 | K3: ='Discount Sheet'!G6 -> 120 | L3: ='Discount Sheet'!G7 -> 3
B4: Environment | C4: Hosting Components | J4: vCores | K4: RAM | L4: HDD | M4: OS | N4: DB
B5: A.1 | C5: eNlight Cloud Hosting | D5: Unit | E5: Cost/Unit | F5: MRC | G5: OTC | H5: Comment | J5: No | K5: GB | L5: GB
A6: 1 | B6: =Quotation!B11 -> SAP ECC DEV | C6: =CONCATENATE("vCores: ",J6," | RAM: ",K6," GB | Performance Storage (0.3 IOPs/GB): ","",L6," GB | OS:",M6," | DB: ",N6,"") -> vCores: 6 | RAM: 32 GB | Performance Storage (0.3 IOPs/GB): 1024 GB | OS:SUSE OS | DB: NA | D6: 1 | E6: =SUM(($J$3*J6)+($K$3*K6)+($L$3*L6)) -> 7632 | F6: =D6*E6 -> 7632 | G6: 0 | H6: As per input | J6: =Quotation!O11 -> 6 | K6: =Quotation!P11 -> 32 | L6: =Quotation!Q11 -> 1024 | M6: SUSE OS | N6: NA
A7: 2 | B7: =Quotation!B13 -> SAP ECC PRD | C7: =CONCATENATE("vCores: ",J7," | RAM: ",K7," GB | Performance Storage (0.3 IOPs/GB): ","",L7," GB | OS:",M7," | DB: ",N7,"") -> vCores: 6 | RAM: 32 GB | Performance Storage (0.3 IOPs/GB): 1024 GB | OS:SUSE OS | DB: NA | D7: 1 | E7: =SUM(($J$3*J7)+($K$3*K7)+($L$3*L7)) -> 7632 | F7: =D7*E7 -> 7632 | G7: 0 | H7: As per input | J7: =Quotation!O13 -> 6 | K7: =Quotation!P13 -> 32 | L7: =Quotation!Q13 -> 1024 | M7: SUSE OS | N7: NA
B8: A.2 | C8: Software Licenses | D8: Unit | E8: Cost/Unit | F8: MRC | G8: OTC | H8: Comment
B9: OS | C9: SUSE OS | D9: =SUM(D6:D7) -> 2 | E9: ='Discount Sheet'!G11 -> 2305 | F9: =D9*E9 -> 4610 | G9: 0 | H9: As per input | I9: =F9/2 -> 2305 | J9: =SUM(J6:J7) -> 12 | K9: =SUM(K6:K7) -> 64 | L9: =SUM(L6:L7) -> 2048
B10: A.3 | C10: Additional Storage & Backup Storage | D10: Unit | E10: Cost/Unit | F10: MRC | G10: OTC | H10: Comment
B11: Backup | C11: Compute Storage ST Nasik Backup Storage BS Per GB 0 3 IOPS | D11: 2000 | E11: ='Discount Sheet'!G7 -> 3 | F11: =D11*E11 -> 6000 | G11: 0
B12: Storage | C12: Block Storage 0 3 IOPS GB | D12: 829 | E12: ='Discount Sheet'!G8 -> 4 | F12: =D12*E12 -> 3316
B13: A.4 | C13: Security Services | D13: Unit | E13: Cost/Unit | F13: MRC | G13: OTC | H13: Comment
B14: Services | C14: Virtual Firewall | D14: 1 | E14: ='Discount Sheet'!G13 -> 15000 | F14: =D14*E14 -> 15000 | G14: 0
B15: A.5 | C15: Network Connectivity Services | D15: Unit | E15: Cost/Unit | F15: MRC | G15: OTC | H15: Comment
B16: Security | C16: Public IP | D16: 2 | E16: ='Discount Sheet'!G16 -> 1500 | F16: =D16*E16 -> 3000 | G16: 0
B17: Security | C17: Internet Bandwidth - (Speed Based) | D17: 10 | E17: ='Discount Sheet'!G15 -> 800 | F17: =D17*E17 -> 8000 | G17: 0
B18: A.6 | C18: Managed Hosting Services | D18: Unit | E18: Cost/Unit | F18: MRC | G18: OTC | H18: Comment
B19: Services | C19: Operating System Management Services | D19: =SUM(D6:D7) -> 2 | E19: ='Discount Sheet'!G19 -> 1500 | F19: =D19*E19 -> 3000 | G19: 0
B20: Services | C20: Storage Management Services -Per TB | D20: 1 | E20: ='Discount Sheet'!G22 -> 500 | F20: =D20*E20 -> 500 | G20: 0
B21: Services | C21: Backup management | D21: 2 | E21: ='Discount Sheet'!G23 -> 1500 | F21: =D21*E21 -> 3000 | G21: 0
B22: Services | C22: vFirewall Management Services | D22: =D14 -> 1 | E22: ='Discount Sheet'!G24 -> 9500 | F22: =D22*E22 -> 9500 | G22: 0
B23: Services | C23: eMagic Cloud Monitoring Softwares | D23: 5 | E23: ='Discount Sheet'!G25 -> 1000 | F23: =D23*E23 -> 5000 | G23: 0 | H23: Basic monitoring
B25: NO. | C25: DESCRIPTION | F25: MRC | G25: OTC
B26: 1 | C26: Infrastructure (A.1 + A.2 + A.3+A.4 +A.5) | F26: =SUM(F6:F17) -> 55190 | G26: =SUM(G6:G17) -> 0
B27: 2 | C27: Managed Services (A.6) | F27: =SUM(F19:F23) -> 21000 | G27: =SUM(G19:G23) -> 0
C28: Total Monthly Service Pay Without Taxes (A.1 + A.2 + A.3 + A.4 +A.5 +A.6) | F28: =SUM(F26:F27) -> 76190 | G28: =SUM(G26:G27) -> 0

Sheet Primary site
B2: ESDS' eNlight Community Cloud Hosting Services - Primary Site (DC Site) | J2: Compute
J3: 120 | K3: 120 | L3: 3.01 | N3: NA | O3: NA
B4: Environment | C4: Hosting Components | J4: vCores | K4: RAM | L4: HDD | M4: IOPS | N4: OS | O4: DB
B5: A.1 | C5: eNlight Cloud Hosting | D5: Unit | E5: Cost/Unit | F5: MRC | G5: OTC | H5: Comment | J5: No | K5: GB | L5: GB | M5: GB
B6: VM 1 | C6: =CONCATENATE("vCores ",J6," | RAM ",K6," GB |Performance Disk (1 IOPs/GB) ",L6," GB | OS ",N6," | DB ",O6,"") -> vCores 4 | RAM 8 GB |Performance Disk (1 IOPs/GB) 200 GB | OS Win | DB NA | D6: 1 | E6: =SUM((J6*J$3)+(K6*K$3)+(L6*L$3)+(M6*M3)) -> 2042 | F6: =D6*E6 -> 2042 | G6: 0 | H6: As per input | J6: 4 | K6: 8 | L6: 200 | M6: =L6*1 -> 200 | N6: Win | O6: NA
B7: A.2 | C7: Software Licenses | D7: Unit | E7: Cost/Unit | F7: MRC | G7: OTC
B8: Services | C8: Operating System - windows core | D8: =J6/2 -> 2 | E8: 750 | F8: =D8*E8 -> 1500 | G8: 0 | H8: As per input
B9: A.3 | C9: Security Services | D9: Unit | E9: Cost/Unit | F9: MRC | G9: OTC
B10: Services | C10: Virtual External Firewall 1 Gbps Throughput | D10: Existing | E10: Existing | F10: Existing | G10: Existing | H10: As per input
B11: Services | C11: Internet Bandwidth - Speed Based | D11: Existing | E11: Existing | F11: Existing | G11: Existing | H11: Existing
B12: Services | C12: Antivirus | D12: 1 | E12: 750 | F12: =D12*E12 -> 750 | G12: 0
B13: Services | C13: Public IP | D13: 1 | E13: 1500 | F13: =D13*E13 -> 1500 | G13: 0
B14: A.4 | C14: Managed Hosting Services | D14: Unit | E14: Cost/Unit | F14: MRC | G14: OTC
B15: Services | C15: Operating System Management Services - Windows | D15: 1 | E15: 1500 | F15: =D15*E15 -> 1500 | G15: 0
B16: Services | C16: Storage Management Services | D16: Existing | E16: Existing | F16: Existing | G16: Existing
B17: Services | C17: Firewall Management Services | D17: Existing | E17: Existing | F17: Existing | G17: Existing | H17: Existing
B18: Services | C18: eMagic Cloud Monitoring | D18: =D6 -> 1 | E18: 1000 | F18: =D18*E18 -> 1000 | G18: 0
B19: NO. | C19: DESCRIPTION | F19: MRC | G19: OTC
B20: 1 | C20: Infrastructure (A.1 + A.2 + A.3) | F20: =SUM(F6:F13) -> 5792 | G20: =SUM(G6:G13) -> 0
B21: 2 | C21: Managed Services (A.5) | F21: =SUM(F15:F18) -> 2500 | G21: =SUM(G15:G18) -> 0
C22: Total Monthly Service Pay Without Taxes (A.1 + A.2 + A.3 + A.4) | F22: =SUM(F20:F21) -> 8292 | G22: =SUM(G20:G21) -> 0
F23: =F22*12 -> 99504

Sheet Sheet2
A1: ESDS Software Solution Pvt Ltd.
A2: Plot No. B-24 & 25, NICE Industrial Area, Satpur MIDC, Nashik 422007.
A5: Submitted To: | B5: Eviden India Private Limited Smruti Ranjan Mishra
A6: Opportunity Title : | B6: Renewal PO
A7: Opportunity Code | B7: POT-16616
A9: Location | B9: Group Name | C9: Group Quantity | D9: Item Name | E9: Item Quantity | I9: Unit
F10: CPU | G10: RAM | H10: Storage | J10: Updated Price (MRP)
A11: Nashik DC | B11: SAP ECC DEV | C11: 1 | D11: vCPU Static Cloud Compute | E11: 1 | F11: 6 | G11: 32 | H11: 1024 | I11: Number | J11: =7632+2305 -> 9937
A12: Nashik DC | D12: SUSE OS Softwares | E12: 1 | I12: Number
A13: Nashik DC | B13: SAP ECC PRD | C13: 1 | D13: vCPU Static Cloud Compute | E13: 1 | F13: 6 | G13: 32 | H13: 1024 | I13: Number | J13: =7632+2305 -> 9937
A14: Nashik DC | D14: SUSE OS Softwares | E14: 1 | I14: Number
A15: Nashik DC | B15: Compute | C15: 1 | D15: Block Storage 0 3 IOPS GB | E15: 829 | I15: GB | J15: 3316
A16: Nashik DC | D16: Compute Storage ST Nasik Backup Storage BS Per GB 0 3 IOPS | E16: 2000 | I16: GB | J16: 6000
A17: Nashik DC | B17: Connectivity | C17: 1 | D17: Speed Based Internet Bandwidth Connectivity | E17: 10 | I17: Mbps | J17: 8000
A18: Nashik DC | B18: Network Connectivity Services | C18: 1 | D18: Public IP - IPv6 | E18: 2 | I18: Number | J18: 3000
A19: Nashik DC | B19: Security Services | C19: 1 | D19: Security Services Virtual Firewall Fortinet VM01 | E19: 1 | I19: Number | J19: 15000
A20: Nashik DC | B20: Managed Services | C20: 1 | D20: SUSE OSMng Managed Services | E20: 2 | I20: Number | J20: 3000
A21: Nashik DC | D21: Virtual Firewall Internal Security Mng Managed Services | E21: 1 | I21: Number | J21: 9500
A22: Nashik DC | D22: Backup Management Managed Services | E22: 2 | I22: VM | J22: 3000
A23: Nashik DC | D23: Storage Management Per TB Storage Mng Managed Services | E23: 1 | I23: TB | J23: 500
A24: Nashik DC | D24: eMagic Cloud Monitoring Softwares | E24: 5 | I24: Number | J24: 5000
A25: Nashik DC | B25: Managed Services | C25: 1 | D25: One Time Cost | E25: 1 | I25: Number
C28: Monthly Total Cost without Taxes (INR) | J28: =SUM(J11:J26) -> 76190
J30: =J28*12 -> 914280

Sheet Discount Sheet
B3: Discount Sheet
C4: Enterprise Storage & Backup Space (IaaS) | D4: UNIT | E4: Price/UNIT | F4: DISCOUNT (%) | G4: Price/UNIT
B5: Iaas | C5: vCPU | D5: 1 | E5: 120 | G5: =(E5-(E5*F5%)) -> 120
B6: Iaas | C6: vRAM | D6: 1 | E6: 120 | G6: =(E6-(E6*F6%)) -> 120
B7: Iaas | C7: Backup storage 0.3 IOPS | D7: 1 | E7: 3 | G7: =(E7-(E7*F7%)) -> 3
B8: Iaas | C8: Block Storage | D8: 1 | E8: 4 | G8: =(E8-(E8*F8%)) -> 4
B9: B.2 | C9: Software as Service (SaaS) | D9: UNIT | E9: Price/UNIT | G9: Price/UNIT
B10: Backup Agent | C10: Backup Agent | D10: 1 | E10: 1000 | G10: =(E10-(E10*F10%)) -> 1000
C11: SUSE OS | D11: 1 | E11: 2305 | G11: =(E11-(E11*F11%)) -> 2305
B12: B.2 | C12: Security As Service | D12: UNIT | E12: Price/UNIT | G12: Price/UNIT
B13: Service | C13: Internal Virtual Firewall 1 Gbps throughput | D13: 1 | E13: 15000 | G13: =(E13-(E13*F13%)) -> 15000
B14: B.2 | C14: Network as Service | D14: UNIT | E14: Price/UNIT | G14: Price/UNIT
B15: Service | C15: Unmetered Internet Bandwidth at Datacenter Site | D15: 1 | E15: 800 | G15: =(E15-(E15*F15%)) -> 800
B16: Service | C16: Public IP | D16: 1 | E16: 1500 | G16: =(E16-(E16*F16%)) -> 1500
B17: Service | C17: Cross Connect + Port Termination - 1 Gbps Fiber Port | D17: 1 | E17: 3000 | G17: =(E17-(E17*F17%)) -> 3000
B18: B.3 | C18: Infra Monitoring and Mgmt and Other Services | D18: UNIT | E18: Price/UNIT | G18: Price/UNIT
B19: Service | C19: Operating System Management | D19: 1 | E19: 1500 | G19: =(E19-(E19*F19%)) -> 1500
B20: Service | C20: PostgresSQL Database Managed Services Up to 100 GB | D20: 1 | E20: 1000 | G20: =(E20-(E20*F20%)) -> 1000
B21: Service | C21: MSSQL Database Managed Services (Up to 100 GB) | D21: 1 | E21: 1000 | G21: =(E21-(E21*F21%)) -> 1000
B22: Service | C22: Storage Management | D22: 1 | E22: 500 | G22: =(E22-(E22*F22%)) -> 500
B23: Service | C23: Backup Management - | D23: 1 | E23: 1500 | G23: =(E23-(E23*F23%)) -> 1500
B24: Service | C24: Security Management Service (Firewall) | D24: 1 | E24: 9500 | G24: =(E24-(E24*F24%)) -> 9500
B25: Service | C25: eMagic basic Monitoring | D25: 1 | E25: 1000 | G25: =(E25-(E25*F25%)) -> 1000

Sheet Quotation
A1: ESDS Software Solution Pvt Ltd.
A2: Plot No. B-24 & 25, NICE Industrial Area, Satpur MIDC, Nashik 422007.
A5: Submitted To: | B5: Eviden India Private Limited Smruti Ranjan Mishra
A6: Opportunity Title : | B6: Renewal PO
A7: Opportunity Code | B7: POT-13814
A9: Location | B9: Group Name | C9: Group Quantity | D9: Item Name | E9: Item Quantity | F9: Unit | G9: Existing | O9: New
G10: Old Product ID | H10: Price | I10: Updated Price | J10: CPU | K10: RAM | L10: Storage | M10: VM Name | N10: IP | O10: CPU | P10: RAM | Q10: Storage | R10: New Product ID | S10: Remarks
A11: Nashik DC | B11: SAP ECC DEV | C11: 1 | D11: vCPU Static Cloud Compute | E11: 6 | F11: Number | G11: 18110 | H11: 7500 | I11: 7632 | J11: 6 | K11: 32 | L11: 1024 | M11: ESDS-4306-18110-eccdev | N11: 10.9.52.196 | O11: 6 | P11: 32 | Q11: 1024 | R11: 62455
A12: Nashik DC | D12: SUSE OS Softwares | E12: 1 | F12: Number | G12: 18116 | I12: 2305 | R12: 21199
A13: Nashik DC | B13: SAP ECC PRD | C13: 1 | D13: vCPU Static Cloud Compute | E13: 6 | F13: Number | G13: 18109 | H13: 7837 | I13: 7632 | J13: 6 | K13: 32 | L13: 1024 | M13: ESDS-4306-18109-eccprd | N13: 10.9.52.194 | O13: 6 | P13: 32 | Q13: 1024 | R13: 62454
A14: Nashik DC | D14: SUSE OS Softwares | E14: 1 | F14: Number | G14: 18116 | I14: 2305 | R14: 21199
A15: Nashik DC | B15: Compute | C15: 1 | D15: Block Storage 0 3 IOPS GB | E15: 829 | F15: GB | G15: 21190 | H15: 3316 | I15: 3316 | R15: 62453
A16: Nashik DC | D16: Compute Storage ST Nasik Backup Storage BS Per GB 0 3 IOPS | E16: 2000 | F16: GB | G16: 18119 | H16: 4000 | I16: 6000 | R16: 62453
A17: Nashik DC | B17: Connectivity | C17: 1 | D17: Speed Based Internet Bandwidth Connectivity | E17: 10 | F17: Mbps | G17: 18121 | H17: 8000 | I17: 8000 | R17: 62452
A18: Nashik DC | B18: Network Connectivity Services | C18: 1 | D18: Public IP - IPv6 | E18: 2 | F18: Number | G18: 18122 | H18: 3000 | I18: 3000 | R18: 62451
A19: Nashik DC | B19: Security Services | C19: 1 | D19: Security Services Virtual Firewall Fortinet VM01 | E19: 1 | F19: Number | H19: 15000 | I19: 15000 | R19: 62450
A20: Nashik DC | B20: Managed Services | C20: 1 | D20: SUSE OSMng Managed Services | E20: 2 | F20: Number | G20: 18123 | H20: 3856.8 | I20: 3000 | R20: 62449
A21: Nashik DC | D21: Virtual Firewall Internal Security Mng Managed Services | E21: 1 | F21: Number | G21: 18123 | H21: 8550 | I21: 9500 | R21: 62449
A22: Nashik DC | D22: Backup Management Managed Services | E22: 2 | F22: VM | G22: 18123 | H22: 3000 | I22: 3000 | R22: 62449
A23: Nashik DC | D23: Storage Management Per TB Storage Mng Managed Services | E23: 1 | F23: TB | G23: 18123 | H23: 500 | I23: 500 | R23: 62449
A24: Nashik DC | D24: eMagic Cloud Monitoring Softwares | E24: 5 | F24: Number | G24: 18123 | H24: 5000 | I24: 5000 | R24: 62449
A25: Nashik DC | B25: Managed Services | C25: 1 | D25: One Time Cost | E25: 1 | F25: Number
H28: =SUM(H11:H26) -> 69559.8 | I28: =SUM(I11:I26) -> 76190
H30: =H28*12 -> 834717.6 | I30: =I28*12 -> 914280
